red_connector_sshfs/__init__.py
red_connector_sshfs/main.py
red_connector_sshfs/sshfs.py
red_connector_sshfs/version.py
red_connector_sshfs-0.2.dist-info/entry_points.txt
red_connector_sshfs-0.2.dist-info/LICENSE
red_connector_sshfs-0.2.dist-info/WHEEL
red_connector_sshfs-0.2.dist-info/METADATA
red_connector_sshfs-0.2.dist-info/RECORD
