Metadata-Version: 2.1
Name: red-connector-sshfs
Version: 0.2
Summary: RED Connector SSHFS is part of the Curious Containers project.
Home-page: https://curious-containers.github.io/
License: AGPL-3.0
Author: Bruno Schilling
Author-email: s0555131@htw-berlin.de
Requires-Python: >=3.4,<4.0
Classifier: License :: OSI Approved :: GNU Affero General Public License v3
Classifier: Programming Language :: Python :: 3
Classifier: Programming Language :: Python :: 3.4
Classifier: Programming Language :: Python :: 3.5
Classifier: Programming Language :: Python :: 3.6
Classifier: Programming Language :: Python :: 3.7
Requires-Dist: cc-connector-cli (>=0.3.0,<0.4.0)
Requires-Dist: jsonschema (>=2.6,<3.0)
Project-URL: Repository, https://github.com/curious-containers/red-connector-sshfs
